setup.py
bwrc_discovery_shared.egg-info/PKG-INFO
bwrc_discovery_shared.egg-info/SOURCES.txt
bwrc_discovery_shared.egg-info/dependency_links.txt
bwrc_discovery_shared.egg-info/requires.txt
bwrc_discovery_shared.egg-info/top_level.txt
discovery_shared/__init__.py
discovery_shared/dataclasses.py
discovery_shared/git.py
discovery_shared/rpc.py
discovery_shared/user.py
discovery_shared/Parameters/__init__.py
discovery_shared/Parameters/parameters.py
discovery_shared/Parameters/parameters_test.py
discovery_shared/Results/__init__.py
discovery_shared/Results/results.py
discovery_shared/auth/__init__.py
discovery_shared/mock/__init__.py
discovery_shared/types/__init__.py